odoo8_addon_account_invoice_tax_required-8.0.1.0.0.99.dev19-py2.7-nspkg.pth
odoo8_addon_account_invoice_tax_required-8.0.1.0.0.99.dev19.dist-info/METADATA
odoo8_addon_account_invoice_tax_required-8.0.1.0.0.99.dev19.dist-info/RECORD
odoo8_addon_account_invoice_tax_required-8.0.1.0.0.99.dev19.dist-info/WHEEL
odoo8_addon_account_invoice_tax_required-8.0.1.0.0.99.dev19.dist-info/namespace_packages.txt
odoo8_addon_account_invoice_tax_required-8.0.1.0.0.99.dev19.dist-info/top_level.txt
odoo_addons/account_invoice_tax_required/README.rst
odoo_addons/account_invoice_tax_required/__init__.py
odoo_addons/account_invoice_tax_required/__openerp__.py
odoo_addons/account_invoice_tax_required/i18n/account_invoice_tax_required.pot
odoo_addons/account_invoice_tax_required/i18n/ar.po
odoo_addons/account_invoice_tax_required/i18n/bg.po
odoo_addons/account_invoice_tax_required/i18n/bs.po
odoo_addons/account_invoice_tax_required/i18n/ca.po
odoo_addons/account_invoice_tax_required/i18n/cs.po
odoo_addons/account_invoice_tax_required/i18n/de.po
odoo_addons/account_invoice_tax_required/i18n/el_GR.po
odoo_addons/account_invoice_tax_required/i18n/en_GB.po
odoo_addons/account_invoice_tax_required/i18n/es.po
odoo_addons/account_invoice_tax_required/i18n/es_CR.po
odoo_addons/account_invoice_tax_required/i18n/es_EC.po
odoo_addons/account_invoice_tax_required/i18n/es_MX.po
odoo_addons/account_invoice_tax_required/i18n/es_PE.po
odoo_addons/account_invoice_tax_required/i18n/et.po
odoo_addons/account_invoice_tax_required/i18n/fi.po
odoo_addons/account_invoice_tax_required/i18n/fr.po
odoo_addons/account_invoice_tax_required/i18n/fr_CA.po
odoo_addons/account_invoice_tax_required/i18n/fr_CH.po
odoo_addons/account_invoice_tax_required/i18n/gl.po
odoo_addons/account_invoice_tax_required/i18n/hr.po
odoo_addons/account_invoice_tax_required/i18n/hr_HR.po
odoo_addons/account_invoice_tax_required/i18n/hu.po
odoo_addons/account_invoice_tax_required/i18n/id.po
odoo_addons/account_invoice_tax_required/i18n/it.po
odoo_addons/account_invoice_tax_required/i18n/ja.po
odoo_addons/account_invoice_tax_required/i18n/lt.po
odoo_addons/account_invoice_tax_required/i18n/mk.po
odoo_addons/account_invoice_tax_required/i18n/mn.po
odoo_addons/account_invoice_tax_required/i18n/nb.po
odoo_addons/account_invoice_tax_required/i18n/nb_NO.po
odoo_addons/account_invoice_tax_required/i18n/nl.po
